docs/to_mdx.py
experiments/amazon-chronos/src/main.py
experiments/amazon-chronos/src/statsforecast_pipeline.py
experiments/amazon-chronos/src/utils.py
experiments/amazon-chronos/src/amazon_chronos/forecaster.py
experiments/amazon-chronos/src/amazon_chronos/pipeline.py
experiments/azure-automl-forecasting/src/evaluation.py
experiments/azure-automl-forecasting/src/nixtla_timegpt.py
experiments/azure-automl-forecasting/src/statsforecast_sn.py
experiments/azure-automl-forecasting/src/azure_automl/__init__.py
experiments/azure-automl-forecasting/src/azure_automl/automl_handler.py
experiments/azure-automl-forecasting/src/azure_automl/download_forecasts.py
experiments/azure-automl-forecasting/src/azure_automl/forecasting.py
experiments/azure-automl-forecasting/src/utils/data_handler.py
experiments/azure-automl-forecasting/src/utils/download_data.py
experiments/azure-automl-forecasting/src/utils/filter_data.py
experiments/efficiency/main.py
experiments/foundation-time-series-arena/tests/__init__.py
experiments/foundation-time-series-arena/tests/test_arena.py
experiments/foundation-time-series-arena/tests/test_eval.py
experiments/foundation-time-series-arena/tests/test_models.py
experiments/foundation-time-series-arena/tests/utils.py
experiments/foundation-time-series-arena/xiuhmolpilli/__init__.py
experiments/foundation-time-series-arena/xiuhmolpilli/arena.py
experiments/foundation-time-series-arena/xiuhmolpilli/models/__init__.py
experiments/foundation-time-series-arena/xiuhmolpilli/models/benchmarks/__init__.py
experiments/foundation-time-series-arena/xiuhmolpilli/models/benchmarks/ml.py
experiments/foundation-time-series-arena/xiuhmolpilli/models/benchmarks/neural.py
experiments/foundation-time-series-arena/xiuhmolpilli/models/benchmarks/prophet.py
experiments/foundation-time-series-arena/xiuhmolpilli/models/benchmarks/stats.py
experiments/foundation-time-series-arena/xiuhmolpilli/models/foundational/__init__.py
nixtla-0.7.1.dist-info/licenses/LICENSE
nixtla-0.7.1.dist-info/METADATA
nixtla-0.7.1.dist-info/WHEEL
nixtla-0.7.1.dist-info/top_level.txt
nixtla-0.7.1.dist-info/RECORD
