Metadata-Version: 2.4
Name: nixtla
Version: 0.7.1
Summary: Python SDK for Nixtla API (TimeGPT)
Author-email: Nixtla <business@nixtla.io>
License: Apache Software License 2.0
Project-URL: Homepage, https://github.com/Nixtla/nixtla/
Project-URL: Documentation, https://nixtlaverse.nixtla.io/
Project-URL: Repository, https://github.com/Nixtla/nixtla/
Keywords: time-series,forecasting,gpt
Classifier: Development Status :: 4 - Beta
Classifier: Intended Audience :: Developers
Classifier: Natural Language :: English
Classifier: License :: OSI Approved :: Apache Software License
Classifier: Programming Language :: Python :: 3.9
Classifier: Programming Language :: Python :: 3.10
Classifier: Programming Language :: Python :: 3.11
Classifier: Programming Language :: Python :: 3.12
Classifier: Programming Language :: Python :: 3.13
Requires-Python: >=3.9
License-File: LICENSE
Requires-Dist: annotated-types
Requires-Dist: httpx[zstd]
Requires-Dist: orjson
Requires-Dist: pandas
Requires-Dist: pydantic>=1.10
Requires-Dist: tenacity
Requires-Dist: tqdm
Requires-Dist: utilsforecast>=0.2.8
Provides-Extra: dev
Requires-Dist: black; extra == "dev"
Requires-Dist: datasetsforecast; extra == "dev"
Requires-Dist: fire; extra == "dev"
Requires-Dist: hierarchicalforecast; extra == "dev"
Requires-Dist: ipython<=8.32.0; extra == "dev"
Requires-Dist: ipywidgets; extra == "dev"
Requires-Dist: jupyterlab; extra == "dev"
Requires-Dist: neuralforecast; extra == "dev"
Requires-Dist: numpy<2; extra == "dev"
Requires-Dist: plotly; extra == "dev"
Requires-Dist: polars; extra == "dev"
Requires-Dist: pre-commit; extra == "dev"
Requires-Dist: pyreadr<0.5.3; extra == "dev"
Requires-Dist: python-dotenv; extra == "dev"
Requires-Dist: pyyaml; extra == "dev"
Requires-Dist: setuptools<70; extra == "dev"
Requires-Dist: statsforecast; extra == "dev"
Requires-Dist: tabulate; extra == "dev"
Requires-Dist: shap; extra == "dev"
Requires-Dist: pytest; extra == "dev"
Requires-Dist: pytest-cov; extra == "dev"
Requires-Dist: pytest-rerunfailures; extra == "dev"
Requires-Dist: pyarrow<21.0.0; extra == "dev"
Requires-Dist: mlforecast; extra == "dev"
Requires-Dist: lightgbm; extra == "dev"
Requires-Dist: utilsforecast[plotting]; extra == "dev"
Requires-Dist: holidays; extra == "dev"
Requires-Dist: pandas_market_calendars; extra == "dev"
Requires-Dist: pip-licenses; extra == "dev"
Provides-Extra: distributed
Requires-Dist: fugue[dask,ray,spark]>=0.8.7; extra == "distributed"
Requires-Dist: dask<=2024.12.1; extra == "distributed"
Requires-Dist: pandas<2.2; extra == "distributed"
Requires-Dist: ray<=2.20.0; extra == "distributed"
Provides-Extra: plotting
Requires-Dist: utilsforecast[plotting]; extra == "plotting"
Provides-Extra: date-extras
Requires-Dist: holidays; extra == "date-extras"
Requires-Dist: pandas_market_calendars; extra == "date-extras"
Dynamic: license-file
